{
  "trial_number": 31,
  "params": {
    "lr": 0.00020522165797944264,
    "weight_decay": 0.00161596588262516,
    "batch_size": 128,
    "dropout": 0.1499539250107677,
    "optimizer": "Adam",
    "scheduler": "cosine",
    "model": "resnet34"
  },
  "best_val_acc": 0.9221,
  "total_gpu_hours": 0.05057060764895545,
  "slurm_task": 4,
  "parallel_workers": 40,
  "sampler": "random",
  "dataset": "cifar10",
  "device": "cuda",
  "accuracy_thresholds": {
    "gpu_h_to_80pct": 0.018748565051290723,
    "gpu_h_to_85pct": 0.02711322956615024,
    "gpu_h_to_90pct": 0.03717155231369866
  },
  "accuracy_curve": {
    "0": {
      "val_acc": 0.5323,
      "gpu_hours": 0.0020543527603149414
    },
    "1": {
      "val_acc": 0.5971,
      "gpu_hours": 0.0037288753853903876
    },
    "2": {
      "val_acc": 0.6818,
      "gpu_hours": 0.005400037037001716
    },
    "3": {
      "val_acc": 0.6421,
      "gpu_hours": 0.007071710427602132
    },
    "4": {
      "val_acc": 0.7395,
      "gpu_hours": 0.00873417701986101
    },
    "5": {
      "val_acc": 0.7555,
      "gpu_hours": 0.010400611758232117
    },
    "6": {
      "val_acc": 0.7382,
      "gpu_hours": 0.012066493299272325
    },
    "7": {
      "val_acc": 0.7768,
      "gpu_hours": 0.013738514847225613
    },
    "8": {
      "val_acc": 0.7721,
      "gpu_hours": 0.015410265723864237
    },
    "9": {
      "val_acc": 0.7963,
      "gpu_hours": 0.017084029780493844
    },
    "10": {
      "val_acc": 0.8265,
      "gpu_hours": 0.018748565051290723
    },
    "11": {
      "val_acc": 0.8081,
      "gpu_hours": 0.020421848230891756
    },
    "12": {
      "val_acc": 0.8352,
      "gpu_hours": 0.02209021766980489
    },
    "13": {
      "val_acc": 0.8291,
      "gpu_hours": 0.02376319858762953
    },
    "14": {
      "val_acc": 0.8249,
      "gpu_hours": 0.025438290768199496
    },
    "15": {
      "val_acc": 0.8539,
      "gpu_hours": 0.02711322956615024
    },
    "16": {
      "val_acc": 0.8654,
      "gpu_hours": 0.028786421683099535
    },
    "17": {
      "val_acc": 0.8648,
      "gpu_hours": 0.030466566615634495
    },
    "18": {
      "val_acc": 0.8777,
      "gpu_hours": 0.03214310334788428
    },
    "19": {
      "val_acc": 0.8857,
      "gpu_hours": 0.03382248348659939
    },
    "20": {
      "val_acc": 0.8957,
      "gpu_hours": 0.03549812873204549
    },
    "21": {
      "val_acc": 0.9009,
      "gpu_hours": 0.03717155231369866
    },
    "22": {
      "val_acc": 0.8989,
      "gpu_hours": 0.038848127921422324
    },
    "23": {
      "val_acc": 0.8993,
      "gpu_hours": 0.04052179190847609
    },
    "24": {
      "val_acc": 0.9133,
      "gpu_hours": 0.042189647952715556
    },
    "25": {
      "val_acc": 0.9174,
      "gpu_hours": 0.043867539366086325
    },
    "26": {
      "val_acc": 0.9177,
      "gpu_hours": 0.045536591476864285
    },
    "27": {
      "val_acc": 0.9206,
      "gpu_hours": 0.04721339311864641
    },
    "28": {
      "val_acc": 0.9205,
      "gpu_hours": 0.048889699114693534
    },
    "29": {
      "val_acc": 0.9221,
      "gpu_hours": 0.05056379497051239
    }
  }
}